usound/__init__.py
usound/__main__.py
usound/autoload.py
usound/logconf_usound.yml
usound/version.py
usound/app/__init__.py
usound/app/app.py
usound/app/install.py
usound/app/commons/__init__.py
usound/app/features/cli/__init__.py
usound/app/features/cli/usound_install_server.py
usound/app/features/cli/usound_speaker_capture.py
usound/app/features/cli/usound_speaker_list.py
usound/app/features/cli/usound_whisper_deploy.py
usound/app/features/cli/usound_whisper_start.py
usound/app/features/cli/usound_whisper_stop.py
usound/app/features/cli/usound_whisper_transcribe.py
usound/app/features/web/__init__.py
usound/app/features/web/usound_web_gui.py
usound/app/features/web/usound_web_versions_usound.py
usound/docker/Dockerfile
usound/docker/__init__.py
usound/docker/docker-compose.yml
usound/docker/__pycache__/__init__.cpython-311.pyc
usound/docker/scripts/start.sh
usound/extensions/features.yml
usound/extensions/user_list.yml
usound/licenses/LICENSE_Jinja2_3_1_6_BSD_License.txt
usound/licenses/LICENSE_MarkupSafe_3_0_2_BSD_License.txt
usound/licenses/LICENSE_PyJWT_2_10_1_MIT_License.txt
usound/licenses/LICENSE_PyYAML_6_0_2_MIT_License.txt
usound/licenses/LICENSE_Pygments_2_19_2_BSD_License.txt
usound/licenses/LICENSE_SoundCard_0_4_4_BSD_License.txt
usound/licenses/LICENSE_Sphinx_8_2_3_UNKNOWN.txt
usound/licenses/LICENSE_alabaster_1_0_0_BSD_License.txt
usound/licenses/LICENSE_annotated-types_0_7_0_MIT_License.txt
usound/licenses/LICENSE_anyio_4_9_0_MIT_License.txt
usound/licenses/LICENSE_argcomplete_3_6_2_Apache_Software_License.txt
usound/licenses/LICENSE_async-timeout_5_0_1_Apache_Software_License.txt
usound/licenses/LICENSE_av_15_0_0_UNKNOWN.txt
usound/licenses/LICENSE_babel_2_17_0_BSD_License.txt
usound/licenses/LICENSE_backports_tarfile_1_2_0_MIT_License.txt
usound/licenses/LICENSE_certifi_2025_7_9_Mozilla_Public_License_2_0-MPL_2_0.txt
usound/licenses/LICENSE_cffi_1_17_1_MIT_License.txt
usound/licenses/LICENSE_charset-normalizer_3_4_2_MIT_License.txt
usound-0.1.7.dist-info/LICENSE.txt
usound-0.1.7.dist-info/METADATA
usound-0.1.7.dist-info/WHEEL
usound-0.1.7.dist-info/entry_points.txt
usound-0.1.7.dist-info/top_level.txt
usound-0.1.7.dist-info/RECORD
